canaerospace/__init__.py
canaerospace/api.py
canaerospace/constants.py
canaerospace/core.py
canaerospace/datatypes.py
canaerospace/directory.py
canaerospace/driver.py
canaerospace/ecu.py
canaerospace/enums.py
canaerospace/errors.py
canaerospace/frame.py
canaerospace/generic_redundancy_resolver.py
canaerospace/instance.py
canaerospace/protocols.py
canaerospace/py.typed
canaerospace/services.py
canaerospace/transmission.py
canaerospace/types.py
canaerospace/units.py
canaerospace/utils.py
canaerospace/identifier_distribution/aircraft_engine.py
canaerospace/identifier_distribution/electric_system_data.py
canaerospace/identifier_distribution/flight_controls.py
canaerospace/identifier_distribution/flight_state.py
canaerospace/identifier_distribution/hydraulic_system_data.py
canaerospace/identifier_distribution/landing_gear.py
canaerospace/identifier_distribution/misc_data.py
canaerospace/identifier_distribution/navigation_data.py
canaerospace/identifier_distribution/power_transmission.py
canaerospace/transmission_slots/__init__.py
canaerospace/transport/__init__.py
canaerospace/transport/socketcan.py
canaerospace/transport/virtual.py
python_canaerospace-0.2.0.dist-info/licenses/LICENSE
python_canaerospace-0.2.0.dist-info/METADATA
python_canaerospace-0.2.0.dist-info/WHEEL
python_canaerospace-0.2.0.dist-info/top_level.txt
python_canaerospace-0.2.0.dist-info/RECORD
