Metadata-Version: 2.4
Name: python-canaerospace
Version: 0.2.0
Summary: Python implementation of the C++ CANaerospace Speciication ( by www.stockflightsystems.com) and the library by mjs513 https://github.com/mjs513/CANaerospace
Author-email: "AIAA UTD Comet Rocketry, Payload" <fenrriquez@gmail.com>
Project-URL: Homepage, https://github.com/AIAA-UTD-Comet-Rocketry/python-canaerospace
Project-URL: Bug Tracker, https://github.com/AIAA-UTD-Comet-Rocketry/python-canaerospace/issues
Classifier: Programming Language :: Python :: 3
Classifier: Operating System :: OS Independent
Classifier: Topic :: Scientific/Engineering
Classifier: Development Status :: 3 - Alpha
Classifier: Topic :: Software Development :: Libraries :: Python Modules
Requires-Python: >=3.10
License-File: LICENSE
Requires-Dist: python-can>=4.3
Requires-Dist: typing-extensions>=4.8
Dynamic: license-file
